{
  "imageName": "DKB_fragm_2161v.jpg",
  "imageWidth": 3043,
  "imageHeight": 1691,
  "annotations": [
    {
      "id": "7af95b94-eae1-4951-ac91-184841d85ef0",
      "classId": 1,
      "bbox": [
        161,
        612,
        454,
        229
      ],
      "confidence": 0.8443,
      "timestamp": "2026-04-28T00:44:19.347127+00:00"
    },
    {
      "id": "07b914f2-a98e-4806-97c8-7b93859021a3",
      "classId": 1,
      "bbox": [
        553,
        1608,
        222,
        58
      ],
      "confidence": 0.7779,
      "timestamp": "2026-04-28T00:44:19.347127+00:00"
    },
    {
      "id": "ad0a9a61-faa6-443e-b465-f42eec1c8e18",
      "classId": 1,
      "bbox": [
        2267,
        635,
        111,
        183
      ],
      "confidence": 0.7461,
      "timestamp": "2026-04-28T00:44:19.347127+00:00"
    },
    {
      "id": "ea89eb62-37d8-472d-9e56-6cef60cb18f1",
      "classId": 1,
      "bbox": [
        862,
        617,
        279,
        217
      ],
      "confidence": 0.7357,
      "timestamp": "2026-04-28T00:44:19.347127+00:00"
    },
    {
      "id": "bfc8e73f-4c7b-44e5-ac1e-1a4252b51bdc",
      "classId": 1,
      "bbox": [
        2701,
        635,
        185,
        204
      ],
      "confidence": 0.7106,
      "timestamp": "2026-04-28T00:44:19.347127+00:00"
    },
    {
      "id": "96bf89b7-3606-4620-9625-0448781ee661",
      "classId": 1,
      "bbox": [
        2329,
        573,
        383,
        277
      ],
      "confidence": 0.7023,
      "timestamp": "2026-04-28T00:44:19.347127+00:00"
    },
    {
      "id": "d25dd5b7-4923-4254-9a17-6e8698026999",
      "classId": 2,
      "bbox": [
        845,
        1540,
        39,
        45
      ],
      "confidence": 0.7003,
      "timestamp": "2026-04-28T00:44:19.347127+00:00"
    },
    {
      "id": "06004115-e68d-4d39-b773-4b02287a9eba",
      "classId": 1,
      "bbox": [
        193,
        1088,
        119,
        121
      ],
      "confidence": 0.6898,
      "timestamp": "2026-04-28T00:44:19.347127+00:00"
    },
    {
      "id": "c7e462a2-2747-41e6-8339-c383a41cd05a",
      "classId": 2,
      "bbox": [
        694,
        1538,
        32,
        52
      ],
      "confidence": 0.6864,
      "timestamp": "2026-04-28T00:44:19.347127+00:00"
    },
    {
      "id": "3c52cdf0-f888-4bff-a834-49b640fbee33",
      "classId": 1,
      "bbox": [
        871,
        932,
        120,
        118
      ],
      "confidence": 0.6725,
      "timestamp": "2026-04-28T00:44:19.347127+00:00"
    },
    {
      "id": "e2c16348-234f-40af-874c-fd66e244b1ed",
      "classId": 1,
      "bbox": [
        628,
        537,
        250,
        308
      ],
      "confidence": 0.6575,
      "timestamp": "2026-04-28T00:44:19.347127+00:00"
    },
    {
      "id": "966b5e0f-6303-4b1d-b6c1-3a5ceea3942b",
      "classId": 1,
      "bbox": [
        1108,
        1100,
        138,
        115
      ],
      "confidence": 0.6523,
      "timestamp": "2026-04-28T00:44:19.347127+00:00"
    },
    {
      "id": "b6e37928-bea7-401d-bda1-c84406ba14ef",
      "classId": 1,
      "bbox": [
        1904,
        627,
        219,
        190
      ],
      "confidence": 0.6514,
      "timestamp": "2026-04-28T00:44:19.347127+00:00"
    },
    {
      "id": "e3f270d6-777c-4487-a32e-5ca7f082f245",
      "classId": 1,
      "bbox": [
        1906,
        610,
        371,
        299
      ],
      "confidence": 0.6493,
      "timestamp": "2026-04-28T00:44:19.347127+00:00"
    },
    {
      "id": "bd9627e4-d1b4-4a7e-8086-d4d8e3448bb0",
      "classId": 1,
      "bbox": [
        2664,
        1080,
        124,
        117
      ],
      "confidence": 0.6328,
      "timestamp": "2026-04-28T00:44:19.347127+00:00"
    },
    {
      "id": "e9500401-7012-4355-8bcc-d449f2552456",
      "classId": 2,
      "bbox": [
        1608,
        1529,
        34,
        86
      ],
      "confidence": 0.6308,
      "timestamp": "2026-04-28T00:44:19.347127+00:00"
    },
    {
      "id": "151f9167-071f-4688-8175-cfd481614634",
      "classId": 2,
      "bbox": [
        538,
        1541,
        34,
        49
      ],
      "confidence": 0.6292,
      "timestamp": "2026-04-28T00:44:19.347127+00:00"
    },
    {
      "id": "fd7d18f4-261a-454f-a006-55f7b97167c0",
      "classId": 1,
      "bbox": [
        199,
        1611,
        102,
        54
      ],
      "confidence": 0.6,
      "timestamp": "2026-04-28T00:44:19.347127+00:00"
    },
    {
      "id": "6af7fdbd-f4cc-483f-bcaf-448b472613a7",
      "classId": 2,
      "bbox": [
        380,
        1539,
        27,
        59
      ],
      "confidence": 0.5999,
      "timestamp": "2026-04-28T00:44:19.347127+00:00"
    },
    {
      "id": "2b6ed14e-3d1c-4b1e-8624-16da87fbec88",
      "classId": 1,
      "bbox": [
        296,
        1609,
        254,
        66
      ],
      "confidence": 0.5953,
      "timestamp": "2026-04-28T00:44:19.347127+00:00"
    },
    {
      "id": "e7c40242-595c-4320-ab7a-8326d916ade2",
      "classId": 1,
      "bbox": [
        2176,
        510,
        133,
        128
      ],
      "confidence": 0.5782,
      "timestamp": "2026-04-28T00:44:19.347127+00:00"
    },
    {
      "id": "54f3b797-d329-4c48-b8f2-d52824612163",
      "classId": 2,
      "bbox": [
        1627,
        1535,
        48,
        64
      ],
      "confidence": 0.5716,
      "timestamp": "2026-04-28T00:44:19.347127+00:00"
    },
    {
      "id": "b03dbb54-2541-4f4c-a583-f4f3474c0f0f",
      "classId": 2,
      "bbox": [
        1295,
        1530,
        37,
        82
      ],
      "confidence": 0.5701,
      "timestamp": "2026-04-28T00:44:19.347127+00:00"
    },
    {
      "id": "4f8f60dd-15f4-43a5-af53-6af0e790469a",
      "classId": 1,
      "bbox": [
        2098,
        625,
        173,
        205
      ],
      "confidence": 0.5602,
      "timestamp": "2026-04-28T00:44:19.347127+00:00"
    },
    {
      "id": "229da601-5f50-4809-a8ce-0357410fe4e0",
      "classId": 1,
      "bbox": [
        1869,
        1544,
        87,
        56
      ],
      "confidence": 0.54,
      "timestamp": "2026-04-28T00:44:19.347127+00:00"
    },
    {
      "id": "110e7e2c-2fb6-4000-89c9-2c4e1a2fe7b3",
      "classId": 1,
      "bbox": [
        484,
        918,
        117,
        121
      ],
      "confidence": 0.5338,
      "timestamp": "2026-04-28T00:44:19.347127+00:00"
    },
    {
      "id": "69a839fd-dc16-4419-8fc1-791b7d823b24",
      "classId": 1,
      "bbox": [
        1141,
        737,
        103,
        81
      ],
      "confidence": 0.5114,
      "timestamp": "2026-04-28T00:44:19.347127+00:00"
    },
    {
      "id": "f6e71541-b1b4-4c10-b7df-93beef775bf4",
      "classId": 1,
      "bbox": [
        1290,
        620,
        148,
        220
      ],
      "confidence": 0.5054,
      "timestamp": "2026-04-28T00:44:19.347127+00:00"
    },
    {
      "id": "d27c6776-0c05-43f5-9ee6-f67e8fdb8ead",
      "classId": 1,
      "bbox": [
        1426,
        640,
        178,
        198
      ],
      "confidence": 0.4999,
      "timestamp": "2026-04-28T00:44:19.347127+00:00"
    },
    {
      "id": "12665a71-79d2-480a-a77e-83a77cfb5795",
      "classId": 3,
      "bbox": [
        34,
        1114,
        2167,
        247
      ],
      "confidence": 0.4941,
      "timestamp": "2026-04-28T00:44:19.347127+00:00"
    },
    {
      "id": "f80c9f63-bc89-43a8-a06f-250bcf02547f",
      "classId": 1,
      "bbox": [
        730,
        639,
        140,
        198
      ],
      "confidence": 0.4864,
      "timestamp": "2026-04-28T00:44:19.347127+00:00"
    },
    {
      "id": "9b9af0c4-99c7-41ca-a12c-af53c91b8896",
      "classId": 2,
      "bbox": [
        662,
        1534,
        24,
        70
      ],
      "confidence": 0.4807,
      "timestamp": "2026-04-28T00:44:19.347127+00:00"
    },
    {
      "id": "30db27ad-1b45-41e7-9d95-6973399a5bd7",
      "classId": 2,
      "bbox": [
        984,
        1534,
        61,
        64
      ],
      "confidence": 0.4797,
      "timestamp": "2026-04-28T00:44:19.347127+00:00"
    },
    {
      "id": "e3551080-9d59-4a04-b379-47fc64a4a0b5",
      "classId": 2,
      "bbox": [
        1295,
        1532,
        50,
        75
      ],
      "confidence": 0.467,
      "timestamp": "2026-04-28T00:44:19.347127+00:00"
    },
    {
      "id": "82e29e68-e144-4d77-9b85-f1da0761d954",
      "classId": 2,
      "bbox": [
        1451,
        1528,
        38,
        85
      ],
      "confidence": 0.4664,
      "timestamp": "2026-04-28T00:44:19.347127+00:00"
    },
    {
      "id": "8d289731-218d-4065-ab6a-f7b64a73cc3a",
      "classId": 2,
      "bbox": [
        1470,
        1537,
        45,
        63
      ],
      "confidence": 0.4355,
      "timestamp": "2026-04-28T00:44:19.347127+00:00"
    },
    {
      "id": "87415df1-7e4f-4850-bc40-75a2e3279941",
      "classId": 1,
      "bbox": [
        1370,
        300,
        144,
        126
      ],
      "confidence": 0.4279,
      "timestamp": "2026-04-28T00:44:19.347127+00:00"
    },
    {
      "id": "cea34292-49e4-4ef8-ab07-e756be6f7f28",
      "classId": 2,
      "bbox": [
        1149,
        1537,
        57,
        56
      ],
      "confidence": 0.4118,
      "timestamp": "2026-04-28T00:44:19.347127+00:00"
    },
    {
      "id": "b18a299e-5e6a-4700-af36-d2892aa68c5f",
      "classId": 2,
      "bbox": [
        1136,
        1533,
        61,
        68
      ],
      "confidence": 0.4083,
      "timestamp": "2026-04-28T00:44:19.347127+00:00"
    },
    {
      "id": "0dda911b-f914-4d36-88b2-8d7c23a5a818",
      "classId": 1,
      "bbox": [
        1127,
        632,
        108,
        116
      ],
      "confidence": 0.3854,
      "timestamp": "2026-04-28T00:44:19.347127+00:00"
    },
    {
      "id": "2776a1e5-a185-4a96-829d-237fad7e460d",
      "classId": 1,
      "bbox": [
        1554,
        986,
        99,
        119
      ],
      "confidence": 0.3847,
      "timestamp": "2026-04-28T00:44:19.347127+00:00"
    },
    {
      "id": "92fd0ce8-11e5-4f52-bce1-b48eb66c125d",
      "classId": 1,
      "bbox": [
        1635,
        1091,
        125,
        114
      ],
      "confidence": 0.3753,
      "timestamp": "2026-04-28T00:44:19.347127+00:00"
    },
    {
      "id": "1ace2821-654f-4d05-b520-7ed64a43bde8",
      "classId": 1,
      "bbox": [
        360,
        630,
        240,
        192
      ],
      "confidence": 0.3596,
      "timestamp": "2026-04-28T00:44:19.347127+00:00"
    },
    {
      "id": "04f26413-3923-4c12-a132-67f1f6eab93e",
      "classId": 2,
      "bbox": [
        1766,
        1535,
        25,
        72
      ],
      "confidence": 0.3579,
      "timestamp": "2026-04-28T00:44:19.347127+00:00"
    },
    {
      "id": "5b7ee081-33fe-4612-baf6-d5c315b202cf",
      "classId": 3,
      "bbox": [
        1194,
        898,
        1789,
        297
      ],
      "confidence": 0.3511,
      "timestamp": "2026-04-28T00:44:19.347127+00:00"
    },
    {
      "id": "2e99706f-e1ab-45f5-9bd9-ea83e966dbc1",
      "classId": 1,
      "bbox": [
        2091,
        623,
        181,
        288
      ],
      "confidence": 0.3381,
      "timestamp": "2026-04-28T00:44:19.347127+00:00"
    },
    {
      "id": "8aaed4a9-67ee-49f3-bc5d-9b75b580d5cd",
      "classId": 1,
      "bbox": [
        166,
        635,
        220,
        185
      ],
      "confidence": 0.3322,
      "timestamp": "2026-04-28T00:44:19.347127+00:00"
    },
    {
      "id": "ca116c79-b8fa-4b33-b8d2-63b644a4f423",
      "classId": 3,
      "bbox": [
        36,
        1450,
        2115,
        138
      ],
      "confidence": 0.3223,
      "timestamp": "2026-04-28T00:44:19.347127+00:00"
    },
    {
      "id": "a5aa69de-7d60-4fef-9f0c-3ae7a159fdbf",
      "classId": 2,
      "bbox": [
        161,
        1527,
        31,
        143
      ],
      "confidence": 0.313,
      "timestamp": "2026-04-28T00:44:19.347127+00:00"
    },
    {
      "id": "077aa0a9-c5bf-4adf-a433-e4676d71548e",
      "classId": 1,
      "bbox": [
        2201,
        560,
        525,
        301
      ],
      "confidence": 0.3104,
      "timestamp": "2026-04-28T00:44:19.347127+00:00"
    },
    {
      "id": "cd6525d4-9d5c-486f-91dc-de5898df3021",
      "classId": 2,
      "bbox": [
        42,
        1526,
        27,
        132
      ],
      "confidence": 0.3038,
      "timestamp": "2026-04-28T00:44:19.347127+00:00"
    },
    {
      "id": "67e8c6a5-889e-43e2-96bd-1adc55053d65",
      "classId": 1,
      "bbox": [
        2643,
        357,
        121,
        120
      ],
      "confidence": 0.3033,
      "timestamp": "2026-04-28T00:44:19.347127+00:00"
    },
    {
      "id": "bb625fce-fc6d-4935-868a-c6e43729b144",
      "classId": 2,
      "bbox": [
        352,
        1528,
        27,
        76
      ],
      "confidence": 0.2956,
      "timestamp": "2026-04-28T00:44:19.347127+00:00"
    },
    {
      "id": "7f607c15-9e7e-49a0-8a6b-36a5fcb1d3e2",
      "classId": 1,
      "bbox": [
        760,
        359,
        119,
        115
      ],
      "confidence": 0.2863,
      "timestamp": "2026-04-28T00:44:19.347127+00:00"
    },
    {
      "id": "1a60b902-e4a9-43ba-bb9f-efbcd73b6ee9",
      "classId": 3,
      "bbox": [
        30,
        968,
        2064,
        228
      ],
      "confidence": 0.2854,
      "timestamp": "2026-04-28T00:44:19.347127+00:00"
    },
    {
      "id": "997b0142-5634-4cf5-987d-f60834721ff8",
      "classId": 1,
      "bbox": [
        1784,
        1534,
        82,
        71
      ],
      "confidence": 0.2828,
      "timestamp": "2026-04-28T00:44:19.347127+00:00"
    },
    {
      "id": "64dcdd9e-1804-4295-b1ec-e23d40567d4c",
      "classId": 3,
      "bbox": [
        1170,
        282,
        1873,
        291
      ],
      "confidence": 0.2818,
      "timestamp": "2026-04-28T00:44:19.347127+00:00"
    },
    {
      "id": "a548a720-8309-47f0-8f20-7abdc9a28a19",
      "classId": 1,
      "bbox": [
        687,
        581,
        193,
        262
      ],
      "confidence": 0.2806,
      "timestamp": "2026-04-28T00:44:19.347127+00:00"
    },
    {
      "id": "83733d5a-656b-47ae-ba8a-a0e7cc8e0041",
      "classId": 1,
      "bbox": [
        1036,
        331,
        116,
        110
      ],
      "confidence": 0.2796,
      "timestamp": "2026-04-28T00:44:19.347127+00:00"
    },
    {
      "id": "9da7657e-80a1-4ac8-a99d-5de3d48b75d8",
      "classId": 1,
      "bbox": [
        245,
        125,
        90,
        126
      ],
      "confidence": 0.2784,
      "timestamp": "2026-04-28T00:44:19.347127+00:00"
    },
    {
      "id": "505ba494-3465-4811-bae2-851677329c23",
      "classId": 2,
      "bbox": [
        2114,
        622,
        49,
        67
      ],
      "confidence": 0.2745,
      "timestamp": "2026-04-28T00:44:19.347127+00:00"
    },
    {
      "id": "9e102237-d548-4b79-92aa-7ae456847157",
      "classId": 2,
      "bbox": [
        1307,
        1539,
        48,
        56
      ],
      "confidence": 0.2717,
      "timestamp": "2026-04-28T00:44:19.347127+00:00"
    },
    {
      "id": "644e2b51-c63d-4443-bd8a-d01049785591",
      "classId": 2,
      "bbox": [
        1608,
        1529,
        68,
        74
      ],
      "confidence": 0.2713,
      "timestamp": "2026-04-28T00:44:19.347127+00:00"
    },
    {
      "id": "734a7093-ee86-496b-a9a4-f14369c8b468",
      "classId": 1,
      "bbox": [
        727,
        750,
        82,
        75
      ],
      "confidence": 0.2692,
      "timestamp": "2026-04-28T00:44:19.347127+00:00"
    },
    {
      "id": "a8d05df2-9455-4e58-8b64-75a399f22100",
      "classId": 2,
      "bbox": [
        849,
        461,
        23,
        140
      ],
      "confidence": 0.269,
      "timestamp": "2026-04-28T00:44:19.347127+00:00"
    },
    {
      "id": "5c61f995-38ad-4bbd-90a9-f43fe55e8a27",
      "classId": 2,
      "bbox": [
        194,
        1527,
        52,
        78
      ],
      "confidence": 0.2665,
      "timestamp": "2026-04-28T00:44:19.347127+00:00"
    },
    {
      "id": "46ddeae9-780b-4f7e-8eb0-47f4b416f2ba",
      "classId": 1,
      "bbox": [
        1791,
        1145,
        122,
        113
      ],
      "confidence": 0.2659,
      "timestamp": "2026-04-28T00:44:19.347127+00:00"
    },
    {
      "id": "5ae06406-1534-4b84-ac5c-89f2b1150fef",
      "classId": 1,
      "bbox": [
        2309,
        1141,
        126,
        120
      ],
      "confidence": 0.2649,
      "timestamp": "2026-04-28T00:44:19.347127+00:00"
    },
    {
      "id": "1d792e48-bb5f-4c91-9af1-8fe3fa6f3744",
      "classId": 1,
      "bbox": [
        1214,
        890,
        113,
        113
      ],
      "confidence": 0.2564,
      "timestamp": "2026-04-28T00:44:19.347127+00:00"
    },
    {
      "id": "34a2ca2c-056f-4168-a49c-c70be724e071",
      "classId": 2,
      "bbox": [
        98,
        1536,
        40,
        35
      ],
      "confidence": 0.2552,
      "timestamp": "2026-04-28T00:44:19.347127+00:00"
    },
    {
      "id": "5d0d3819-eb7a-403a-ac86-b2933c2b6cf9",
      "classId": 2,
      "bbox": [
        200,
        1532,
        60,
        61
      ],
      "confidence": 0.2551,
      "timestamp": "2026-04-28T00:44:19.347127+00:00"
    }
  ]
}